{
    "Ar36": {
        "error": 0.00013712560081183042,
        "error_type": "",
        "fit": "previous",
        "references": [
            {
                "exclude": false,
                "record_id": "ba-01-A-18920"
            }
        ],
        "value": 0.0029765064153389567
    },
    "Ar37": {
        "error": 0.008389807129611944,
        "error_type": "",
        "fit": "previous",
        "references": [
            {
                "exclude": false,
                "record_id": "ba-01-A-18920"
            }
        ],
        "value": -0.011394119080559458
    },
    "Ar38": {
        "error": 0.010846893085695817,
        "error_type": "",
        "fit": "previous",
        "references": [
            {
                "exclude": false,
                "record_id": "ba-01-A-18920"
            }
        ],
        "value": 0.010243924723282538
    },
    "Ar39": {
        "error": 0.008505129426814015,
        "error_type": "",
        "fit": "previous",
        "references": [
            {
                "exclude": false,
                "record_id": "ba-01-A-18920"
            }
        ],
        "value": 0.016628001744390195
    },
    "Ar40": {
        "error": 0.022919325784853558,
        "error_type": "",
        "fit": "previous",
        "references": [
            {
                "exclude": false,
                "record_id": "ba-01-A-18920"
            }
        ],
        "value": 0.921947828948
    }
}