{
    "Ar36": {
        "error": 0.00013664106599731545,
        "error_type": "",
        "fit": "previous",
        "references": [
            {
                "exclude": false,
                "record_id": "ba-01-A-26057"
            }
        ],
        "value": 0.003602333590944713
    },
    "Ar37": {
        "error": 0.008996242410950601,
        "error_type": "",
        "fit": "previous",
        "references": [
            {
                "exclude": false,
                "record_id": "ba-01-A-26057"
            }
        ],
        "value": 0.01671405371469894
    },
    "Ar38": {
        "error": 0.011040154903676755,
        "error_type": "",
        "fit": "previous",
        "references": [
            {
                "exclude": false,
                "record_id": "ba-01-A-26057"
            }
        ],
        "value": 0.021132859880347753
    },
    "Ar39": {
        "error": 0.009425242714266324,
        "error_type": "",
        "fit": "previous",
        "references": [
            {
                "exclude": false,
                "record_id": "ba-01-A-26057"
            }
        ],
        "value": 0.029938947022351232
    },
    "Ar40": {
        "error": 0.022352885068616095,
        "error_type": "",
        "fit": "previous",
        "references": [
            {
                "exclude": false,
                "record_id": "ba-01-A-26057"
            }
        ],
        "value": 0.6125179105163321
    }
}