{
    "Ar36": {
        "error": 0.00017349035624019914,
        "error_type": "",
        "fit": "previous",
        "references": [
            {
                "exclude": false,
                "record_id": "ba-01-A-18194"
            }
        ],
        "value": 0.0038017558812559853
    },
    "Ar37": {
        "error": 0.008760918120458571,
        "error_type": "",
        "fit": "previous",
        "references": [
            {
                "exclude": false,
                "record_id": "ba-01-A-18194"
            }
        ],
        "value": 0.00019733058703001564
    },
    "Ar38": {
        "error": 0.010006376883183479,
        "error_type": "",
        "fit": "previous",
        "references": [
            {
                "exclude": false,
                "record_id": "ba-01-A-18194"
            }
        ],
        "value": 0.0016142780081481829
    },
    "Ar39": {
        "error": 0.008552978393847544,
        "error_type": "",
        "fit": "previous",
        "references": [
            {
                "exclude": false,
                "record_id": "ba-01-A-18194"
            }
        ],
        "value": 0.0393775705167341
    },
    "Ar40": {
        "error": 0.02459183653545427,
        "error_type": "",
        "fit": "previous",
        "references": [
            {
                "exclude": false,
                "record_id": "ba-01-A-18194"
            }
        ],
        "value": 1.2818633814864018
    }
}