{
    "Ar36": {
        "error": 0.00021427634316538015,
        "error_type": "",
        "fit": "previous",
        "references": [
            {
                "exclude": false,
                "record_id": "ba-01-A-16520"
            }
        ],
        "value": 0.00820540994787456
    },
    "Ar37": {
        "error": 0.009359551194566905,
        "error_type": "",
        "fit": "previous",
        "references": [
            {
                "exclude": false,
                "record_id": "ba-01-A-16520"
            }
        ],
        "value": -0.01611935638590942
    },
    "Ar38": {
        "error": 0.012367000449205747,
        "error_type": "",
        "fit": "previous",
        "references": [
            {
                "exclude": false,
                "record_id": "ba-01-A-16520"
            }
        ],
        "value": -0.009378461592704035
    },
    "Ar39": {
        "error": 0.009504775915687888,
        "error_type": "",
        "fit": "previous",
        "references": [
            {
                "exclude": false,
                "record_id": "ba-01-A-16520"
            }
        ],
        "value": 0.0233084006943527
    },
    "Ar40": {
        "error": 0.028601388826457772,
        "error_type": "",
        "fit": "previous",
        "references": [
            {
                "exclude": false,
                "record_id": "ba-01-A-16520"
            }
        ],
        "value": 2.548271265787098
    }
}