{
    "Ar36": {
        "error": 0.0006154943691967307,
        "error_type": "",
        "fit": "previous",
        "references": [
            {
                "exclude": false,
                "record_id": "ba-01-A-15087"
            }
        ],
        "value": 0.013422490940683087
    },
    "Ar37": {
        "error": 0.010194767483458652,
        "error_type": "",
        "fit": "previous",
        "references": [
            {
                "exclude": false,
                "record_id": "ba-01-A-15087"
            }
        ],
        "value": 0.009951397447645125
    },
    "Ar38": {
        "error": 0.011576753586848617,
        "error_type": "",
        "fit": "previous",
        "references": [
            {
                "exclude": false,
                "record_id": "ba-01-A-15087"
            }
        ],
        "value": 0.007477650260428492
    },
    "Ar39": {
        "error": 0.01813448459212898,
        "error_type": "",
        "fit": "previous",
        "references": [
            {
                "exclude": false,
                "record_id": "ba-01-A-15087"
            }
        ],
        "value": 0.060336894300023064
    },
    "Ar40": {
        "error": 0.04335754948614579,
        "error_type": "",
        "fit": "previous",
        "references": [
            {
                "exclude": false,
                "record_id": "ba-01-A-15087"
            }
        ],
        "value": 4.409945405340606
    }
}