{
    "Ar36": {
        "error": 0.00030143270758119776,
        "error_type": "",
        "fit": "previous",
        "references": [
            {
                "exclude": false,
                "record_id": "ba-01-A-17745"
            }
        ],
        "value": 0.008178304151340247
    },
    "Ar37": {
        "error": 0.010122201176058885,
        "error_type": "",
        "fit": "previous",
        "references": [
            {
                "exclude": false,
                "record_id": "ba-01-A-17745"
            }
        ],
        "value": -0.0005514672967087695
    },
    "Ar38": {
        "error": 0.01153014051224724,
        "error_type": "",
        "fit": "previous",
        "references": [
            {
                "exclude": false,
                "record_id": "ba-01-A-17745"
            }
        ],
        "value": -9.139199340284839e-05
    },
    "Ar39": {
        "error": 0.0081123833917519,
        "error_type": "",
        "fit": "previous",
        "references": [
            {
                "exclude": false,
                "record_id": "ba-01-A-17745"
            }
        ],
        "value": 0.08016888181067132
    },
    "Ar40": {
        "error": 0.05736589114125704,
        "error_type": "",
        "fit": "previous",
        "references": [
            {
                "exclude": false,
                "record_id": "ba-01-A-17745"
            }
        ],
        "value": 2.8845021175527616
    }
}