{
    "Ar36": {
        "error": 0.00017342377619887112,
        "error_type": "",
        "fit": "previous",
        "references": [
            {
                "exclude": false,
                "record_id": "ba-01-A-17676"
            }
        ],
        "value": 0.005873529931481647
    },
    "Ar37": {
        "error": 0.008704115134123738,
        "error_type": "",
        "fit": "previous",
        "references": [
            {
                "exclude": false,
                "record_id": "ba-01-A-17676"
            }
        ],
        "value": -0.003702322710682507
    },
    "Ar38": {
        "error": 0.011257738750773287,
        "error_type": "",
        "fit": "previous",
        "references": [
            {
                "exclude": false,
                "record_id": "ba-01-A-17676"
            }
        ],
        "value": 0.015055262010355983
    },
    "Ar39": {
        "error": 0.008687833952695451,
        "error_type": "",
        "fit": "previous",
        "references": [
            {
                "exclude": false,
                "record_id": "ba-01-A-17676"
            }
        ],
        "value": 0.017722516475410604
    },
    "Ar40": {
        "error": 0.023248125927447048,
        "error_type": "",
        "fit": "previous",
        "references": [
            {
                "exclude": false,
                "record_id": "ba-01-A-17676"
            }
        ],
        "value": 1.8694006666528662
    }
}