{
    "Ar36": {
        "error": 0.0002635125093387446,
        "error_type": "",
        "fit": "previous",
        "references": [
            {
                "exclude": false,
                "record_id": "ba-01-A-29033"
            }
        ],
        "value": 0.01476447989137789
    },
    "Ar37": {
        "error": 0.008729570499443352,
        "error_type": "",
        "fit": "previous",
        "references": [
            {
                "exclude": false,
                "record_id": "ba-01-A-29033"
            }
        ],
        "value": 0.033633124385093804
    },
    "Ar38": {
        "error": 0.010701730960572206,
        "error_type": "",
        "fit": "previous",
        "references": [
            {
                "exclude": false,
                "record_id": "ba-01-A-29033"
            }
        ],
        "value": 0.019791358228122197
    },
    "Ar39": {
        "error": 0.008658513793110846,
        "error_type": "",
        "fit": "previous",
        "references": [
            {
                "exclude": false,
                "record_id": "ba-01-A-29033"
            }
        ],
        "value": 0.01809639768130389
    },
    "Ar40": {
        "error": 0.021120638358558385,
        "error_type": "",
        "fit": "previous",
        "references": [
            {
                "exclude": false,
                "record_id": "ba-01-A-29033"
            }
        ],
        "value": 3.939596106447283
    }
}